polygon_mcp/__init__.py
polygon_mcp/server.py
polygon_mcp-0.1.0.dist-info/METADATA
polygon_mcp-0.1.0.dist-info/WHEEL
polygon_mcp-0.1.0.dist-info/entry_points.txt
polygon_mcp-0.1.0.dist-info/RECORD
