Metadata-Version: 2.4
Name: polygon-mcp
Version: 0.1.0
Summary: MCP server wrapping Polygon.io Python SDK for stocks, options, forex, and crypto
Project-URL: Homepage, https://github.com/atomcp-ai/polygon-mcp
Project-URL: Repository, https://github.com/atomcp-ai/polygon-mcp
Project-URL: Issues, https://github.com/atomcp-ai/polygon-mcp/issues
Author: atomcp-ai
License: MIT
Keywords: api,crypto,forex,mcp,options,polygon,polygon.io,stocks,trading
Classifier: Development Status :: 4 - Beta
Classifier: Intended Audience :: Developers
Classifier: License :: OSI Approved :: MIT License
Classifier: Programming Language :: Python :: 3
Classifier: Programming Language :: Python :: 3.10
Classifier: Programming Language :: Python :: 3.11
Classifier: Programming Language :: Python :: 3.12
Requires-Python: >=3.10
Requires-Dist: mcp>=1.0.0
Requires-Dist: polygon>=1.2.8
